{
  "name": "Chris Lake",
  "monthly_listeners": 8453882,
  "followers": 370095,
  "verified": true,
  "top_cities": [
    {
      "city": "Sydney",
      "country": "AU",
      "region": "NSW",
      "listeners": 188360
    },
    {
      "city": "Melbourne",
      "country": "AU",
      "region": "VIC",
      "listeners": 157338
    },
    {
      "city": "Brisbane",
      "country": "AU",
      "region": "QLD",
      "listeners": 123438
    },
    {
      "city": "London",
      "country": "GB",
      "region": "ENG",
      "listeners": 119606
    },
    {
      "city": "Los Angeles",
      "country": "US",
      "region": "CA",
      "listeners": 114834
    }
  ],
  "social_links": {
    "facebook": "https://facebook.com/chrislake",
    "instagram": "https://instagram.com/chrislake",
    "twitter": "https://twitter.com/chrislake",
    "wikipedia": "https://en.wikipedia.org/wiki/Chris_Lake"
  },
  "upcoming_concerts": [
    {
      "title": "Chris Lake",
      "date": "2025-05-09T19:00+10:00",
      "location": {
        "name": "PICA (Port Melbourne Industrial Centre for the Arts)",
        "city": "Port Melbourne"
      },
      "festival": false
    },
    {
      "title": "Chris Lake",
      "date": "2025-05-10T19:15+10:00",
      "location": {
        "name": "Hordern Pavilion",
        "city": "Moore Park "
      },
      "festival": false
    },
    {
      "title": "Breakaway Music Festival Atlanta 2025",
      "date": "2025-05-16T00:00-04:00",
      "location": {
        "name": "Center Parc Credit Union Stadium Victory Plaza",
        "city": "Atlanta"
      },
      "festival": true
    },
    {
      "title": "Chris Lake, deadmau5, Excision, Galantis, Kaskade, Louis The Child, Of The Trees, Rezz, RL Grime, Seven Lions, Sofi Tukker, Timmy Trumpet, SVDDEN DEATH, Zedd, Zeds Dead, Apashe, Benny Benassi, Detox Unit, Kai Wachi, KREAM, LP Giobbi, NGHTMRE, Dimension, PEEKABOO, Caspa, Ray Volpe, Tinlicker, Wax Motif, BONNIE X CLYDE, Distinct Motive, Heyz, Ian Asher, Jon Casey, Joshwa, Juelz, Kaleena Zanders, Lil Texas, MC4D, Skepsis, Westend, YOOKiE, Audiofreq, Caster, Control Freak, Darksiderz, Dennett, Muzz, Kreation, Dogma, Prosecute, Pyke, Rohaan, Seth David, Sherm, The Stooges, VKTM, Pyke, Taiki Nulight",
      "date": "2025-08-29T00:00-05:00",
      "location": {
        "name": "SeatGeek Stadium",
        "city": "Bridgeview"
      },
      "festival": false
    }
  ]
}